mooring_data_generator/__init__.py
mooring_data_generator/builder.py
mooring_data_generator/cli.py
mooring_data_generator/file_worker.py
mooring_data_generator/http_worker.py
mooring_data_generator/models.py
mooring_data_generator/openapi.py
mooring_data_generator/receiver.py
mooring_data_generator-2.3.0.dist-info/WHEEL
mooring_data_generator-2.3.0.dist-info/entry_points.txt
mooring_data_generator-2.3.0.dist-info/METADATA
mooring_data_generator-2.3.0.dist-info/RECORD
