Metadata-Version: 2.3
Name: mooring-data-generator
Version: 2.3.0
Summary: Random-data generator to simulate fictional port data flows for use at a Hackathon
Author: Ben Fitzhardinge
Author-email: Ben Fitzhardinge <ben@benjamin.dog>
Classifier: Development Status :: 4 - Beta
Classifier: Intended Audience :: Developers
Classifier: Topic :: Software Development :: Testing :: Traffic Generation
Classifier: Programming Language :: Python :: 3
Classifier: Programming Language :: Python :: 3.10
Classifier: Programming Language :: Python :: 3.11
Classifier: Programming Language :: Python :: 3.12
Classifier: Programming Language :: Python :: 3.13
Classifier: Programming Language :: Python :: 3.14
Requires-Dist: pydantic>=2.8
Maintainer: Ben Fitzhardinge
Maintainer-email: Ben Fitzhardinge <ben@benjamin.dog>
Requires-Python: >=3.10
Project-URL: Changelog, https://github.com/bendog/mooring-data-generator/releases
Project-URL: Homepage, https://github.com/bendog/mooring-data-generator
Project-URL: Issues, https://github.com/bendog/mooring-data-generator/issues
Project-URL: Repository, https://github.com/bendog/mooring-data-generator
